brokenxapi/__init__.py
brokenxapi/__version__.py
brokenxapi/auth.py
brokenxapi/cli.py
brokenxapi/client.py
brokenxapi/exceptions.py
brokenxapi/models.py
brokenxapi-2.0.3.dist-info/licenses/LICENSE
brokenxapi-2.0.3.dist-info/METADATA
brokenxapi-2.0.3.dist-info/WHEEL
brokenxapi-2.0.3.dist-info/entry_points.txt
brokenxapi-2.0.3.dist-info/top_level.txt
brokenxapi-2.0.3.dist-info/RECORD
