Metadata-Version: 2.4
Name: BROKENXAPI
Version: 2.0.3
Summary: Official async Python SDK and CLI for BrokenX YouTube API
Author-email: Mr Broken <brokenxnetwork@gmail.com>
License: MIT License
Project-URL: Homepage, https://github.com/mrxbroken011/BROKENXAPI
Project-URL: Repository, https://github.com/mrxbroken011/BROKENXAPI
Project-URL: Documentation, https://brokenxapi-docs.vercel.app
Project-URL: Issues, https://github.com/mrxbroken011/BROKENXAPI/issues
Keywords: brokenx,youtube,api,async,sdk,cli,aiohttp,telegram
Classifier: Development Status :: 5 - Production/Stable
Classifier: Intended Audience :: Developers
Classifier: Topic :: Software Development :: Libraries
Classifier: Topic :: Multimedia :: Video
Classifier: License :: OSI Approved :: MIT License
Classifier: Operating System :: OS Independent
Classifier: Programming Language :: Python :: 3
Classifier: Programming Language :: Python :: 3 :: Only
Classifier: Programming Language :: Python :: 3.8
Classifier: Programming Language :: Python :: 3.9
Classifier: Programming Language :: Python :: 3.10
Classifier: Programming Language :: Python :: 3.11
Classifier: Programming Language :: Python :: 3.12
Classifier: Framework :: AsyncIO
Requires-Python: >=3.8
License-File: LICENSE
Requires-Dist: aiohttp>=3.8.0
Dynamic: license-file
